tri3d/__init__.py
tri3d/camera.py
tri3d/geometry.py
tri3d/misc.py
tri3d/plot.py
tri3d/quaternion.py
tri3d/datasets/__init__.py
tri3d/datasets/align_nuscenes.py
tri3d/datasets/argoverse.py
tri3d/datasets/dataset.py
tri3d/datasets/nuscenes.py
tri3d/datasets/once.py
tri3d/datasets/optimize_waymo.py
tri3d/datasets/semantickitti.py
tri3d/datasets/waymo.py
tri3d/datasets/zod_frames.py
tri3d-0.2.2.dist-info/licenses/LICENSE.txt
tri3d-0.2.2.dist-info/METADATA
tri3d-0.2.2.dist-info/WHEEL
tri3d-0.2.2.dist-info/top_level.txt
tri3d-0.2.2.dist-info/RECORD
