Metadata-Version: 2.4
Name: tri3d
Version: 0.2.2
Summary: A unified interface to various 3D driving datasets
Author-email: Nicolas Granger <nicolas.granger@cea.fr>
License-Expression: CECILL-C
Classifier: Programming Language :: Python :: 3 :: Only
Classifier: Programming Language :: Python :: 3.11
Classifier: Programming Language :: Python :: 3.12
Classifier: Programming Language :: Python :: 3.13
Requires-Python: >=3.11
License-File: LICENSE.txt
Requires-Dist: numba
Requires-Dist: numpy
Requires-Dist: pillow
Requires-Dist: pyarrow
Provides-Extra: align-nuscenes
Requires-Dist: torch; extra == "align-nuscenes"
Requires-Dist: torch-cluster; extra == "align-nuscenes"
Requires-Dist: tqdm; extra == "align-nuscenes"
Provides-Extra: plot
Requires-Dist: k3d; extra == "plot"
Requires-Dist: matplotlib; extra == "plot"
Dynamic: license-file
